verysimplemodule_guilherme/__init__.py
verysimplemodule_guilherme/substract.py
verysimplemodule_guilherme/extra/__init__.py
verysimplemodule_guilherme/extra/divide.py
verysimplemodule_guilherme/extra/multiple.py
verysimplemodule_guilherme-0.0.1.dist-info/METADATA
verysimplemodule_guilherme-0.0.1.dist-info/WHEEL
verysimplemodule_guilherme-0.0.1.dist-info/top_level.txt
verysimplemodule_guilherme-0.0.1.dist-info/RECORD
