Metadata-Version: 2.1
Name: verysimplemodule-guilherme
Version: 0.0.1
Summary: Pacote de teste
Author: Guilherme
Author-email: guilherme.silva@ufpi.edu.br
Keywords: python,pacote,teste
Classifier: Development Status :: 3 - Alpha
Classifier: Intended Audience :: Developers
Classifier: Programming Language :: Python :: 3
Requires-Dist: scikit-image
Requires-Dist: numpy
Requires-Dist: matplotlib
